<?xml version="1.0" encoding="UTF-8"?>
<list xmlns:xsi="http://www.w3.org/2001/XMLSchema-instance" xsi:noNamespaceSchemaLocation="../../../xsd/npcs.xsd">
    <npc id="20093" level="15" type="L2Monster" name="Orc Fighter" title="L2 Angel" usingServerSideTitle="true">
        <!-- Confirmed CT2.5 -->
        <parameters>
            <param name="MoveAroundSocial" value="75" />
            <param name="MoveAroundSocial1" value="75" />
            <param name="MoveAroundSocial2" value="75" />
            <param name="SetHateRaceRatio" value="10" />
            <param name="SetAggressiveTime" value="0" />
        </parameters>
        <race>HUMANOID</race>
        <sex>MALE</sex>
        <equipment rhand="1" /> <!-- rhand: Short Sword -->
        <acquire expRate="0.5" sp="60" />
        <stats str="40" int="21" dex="30" wit="20" con="43" men="20">
            <vitals hp="163.28607" hpRegen="2" mp="108.4" mpRegen="0.9" />
            <attack physical="40.33758" magical="13.20506" random="30" critical="4" accuracy="4.75" attackSpeed="253" type="SWORD" range="40" distance="80" width="120" />
            <defence physical="500.82527" magical="80.16396260604" />
            <attribute>
                <defence fire="20" water="20" wind="20" earth="20" holy="20" dark="20" />
            </attribute>
            <speed>
                <walk ground="45" />
                <run ground="110" />
            </speed>
            <hitTime>460</hitTime>
        </stats>
        <status undying="false" canBeSown="true" />
        <skillList>
            <skill id="4408" level="1" /> <!--HP Increase (1x) -->
            <skill id="4409" level="1" /> <!--MP Increase (1x) -->
            <skill id="4410" level="11" /> <!--Average P. Atk. -->
            <skill id="4411" level="11" /> <!--Average M. Atk. -->
            <skill id="4412" level="11" /> <!--Average P. Def. -->
            <skill id="4413" level="11" /> <!--Average M. Def. -->
            <skill id="4414" level="2" /> <!--Standard Type -->
            <skill id="4415" level="3" /> <!--One-handed Sword -->
            <skill id="4416" level="6" /> <!--Humanoids -->
        </skillList>
        <exCrtEffect>false</exCrtEffect>
        <ai  isAggressive="false">
            <clanList>
                <clan>ORC</clan>
            </clanList>
        </ai>
        <dropLists>
            <death>
                <group chance="70">
                    <item id="57" min="9800" max="13200" chance="100" /> <!-- Adena -->
                </group>
            </death>
        </dropLists>
        <collision>
            <radius normal="12" grown="14" />
            <height normal="22" grown="26.4" />
        </collision>
    </npc>
    <npc id="20936" level="35" type="L2Monster" name="Tanor Silenos" title="L2 Angel" usingServerSideTitle="true">
        <!-- Confirmed CT2.5 -->
        <parameters>
            <param name="MoveAroundSocial" value="100" />
            <param name="MoveAroundSocial1" value="50" />
            <param name="MoveAroundSocial2" value="100" />
            <param name="SoulShot" value="100" />
            <param name="SoulShotRate" value="10" />
            <param name="SpiritShot" value="100" />
            <param name="SpiritShotRate" value="5" />
            <param name="LongRangeGuardRate" value="5" />
            <skill name="Buff" id="4103" level="2" /> <!-- NPC Ultimate Evasion -->
        </parameters>
        <race>HUMANOID</race>
        <sex>MALE</sex>
        <equipment rhand="88" /> <!-- rhand: Morning Star -->
        <acquire expRate="2" sp="100" />
        <stats str="40" int="21" dex="30" wit="20" con="35" men="15">
            <vitals hp="966.57792" hpRegen="4.5" mp="478.8" mpRegen="1.8" />
            <attack physical="300.36077" magical="300.43155" random="50" critical="1" accuracy="9" attackSpeed="253" type="BLUNT" range="40" distance="80" width="120" />
            <defence physical="300.55035" magical="5.232986928232" />
            <attribute>
                <defence fire="20" water="20" wind="20" earth="20" holy="20" dark="20" />
            </attribute>
            <speed>
                <walk ground="34" />
                <run ground="174" />
            </speed>
            <hitTime>460</hitTime>
        </stats>
        <status undying="false" canBeSown="true" />
        <skillList>
            <skill id="4103" level="2" /> <!--NPC Ultimate Evasion -->
            <skill id="4408" level="9" /> <!--HP Increase (1/2x) -->
            <skill id="4409" level="1" /> <!--MP Increase (1x) -->
            <skill id="4410" level="11" /> <!--Average P. Atk. -->
            <skill id="4411" level="11" /> <!--Average M. Atk. -->
            <skill id="4412" level="11" /> <!--Average P. Def. -->
            <skill id="4414" level="2" /> <!--Standard Type -->
            <skill id="4415" level="5" /> <!--Blunt Weapons -->
            <skill id="4416" level="6" /> <!--Humanoids -->
        </skillList>
        <shots shotChance="30" spiritChance="30" />
        <exCrtEffect>false</exCrtEffect>
        <sNpcPropHpRate>0.5</sNpcPropHpRate>
        <ai aggroRange="1000" isAggressive="false">
            <clanList>
                <clan>SILENOS</clan>
            </clanList>
        </ai>
        <dropLists>
            <death>
                <group chance="70">
                    <item id="57" min="28300" max="56500" chance="100" /> <!-- Adena -->
                </group>
            </death>
        </dropLists>
        <collision>
            <radius normal="13" />
            <height normal="29" />
        </collision>
    </npc>

    <npc id="29026" level="60" type="L2Monster" name="Pirate Zombie Captain" title="L2 Angel" usingServerSideTitle="true">
        <!-- Confirmed CT2.5 -->
        <parameters>
            <param name="MoveAroundSocial" value="70" />
            <param name="MoveAroundSocial1" value="70" />
            <param name="MoveAroundSocial2" value="70" />
        </parameters>
        <race>UNDEAD</race>
        <sex>MALE</sex>
        <equipment rhand="232" /> <!-- rhand: Dark Elven Dagger -->
        <acquire expRate="1.5" sp="100"/>
        <stats str="40" int="21" dex="30" wit="20" con="43" men="20">
            <vitals hp="1933" hpRegen="6.5" mp="804.0" mpRegen="2.4" />
            <attack physical="600" magical="600" random="10" critical="8" accuracy="0" attackSpeed="253" type="DAGGER" range="40" distance="80" width="120" />
            <defence physical="400" magical="400" />
            <attribute>
                <attack type="DARK" value="20" />
                <defence fire="20" water="20" wind="20" earth="20" holy="-32" dark="53" />
            </attribute>
            <speed>
                <walk ground="14" />
                <run ground="140" />
            </speed>
            <hitTime>760</hitTime>
        </stats>
        <status undying="false" noSleepMode="true" />
        <skillList>
            <skill id="4045" level="1" /> <!--Resist Full Magic Attack -->
            <skill id="4408" level="1" /> <!--HP Increase (1x) -->
            <skill id="4409" level="1" /> <!--MP Increase (1x) -->
            <skill id="4410" level="11" /> <!--Average P. Atk. -->
            <skill id="4411" level="11" /> <!--Average M. Atk. -->
            <skill id="4412" level="11" /> <!--Average P. Def. -->
            <skill id="4413" level="11" /> <!--Average M. Def. -->
            <skill id="4414" level="2" /> <!--Standard Type -->
            <skill id="4415" level="7" /> <!--Daggers -->
            <skill id="4416" level="1" /> <!--Undead -->
        </skillList>
        <exCrtEffect>true</exCrtEffect>
        <ai aggroRange="300"  isAggressive="false" />
        <dropLists>
            <death>
                <group chance="20">
                    <item id="57" min="80000" max="100000" chance="100" /> <!-- Greater Healing Potion -->
                </group>
            </death>
        </dropLists>
        <collision>
            <radius normal="17" />
            <height normal="28" />
        </collision>
    </npc>
    <npc id="22815" level="81" type="L2Monster" name="Drakos" title="L2 Angel" usingServerSideTitle="true" usingServerSideName="true">
        <!-- Confirmed CT2.5 -->
        <parameters>
            <skill name="Skill01_ID" id="6845" level="1" /> <!-- Power Strike -->
        </parameters>
        <race>UNDEAD</race>
        <sex>MALE</sex>
        <equipment rhand="13985" lhand="13986" /> <!-- rhand: Exclusive to Monsters (Death Slayer_r) lhand: Exclusive to Monsters (Death Slayer_l) -->
        <acquire expRate="8" sp="100" />
        <stats str="40" int="21" dex="30" wit="20" con="43" men="20">
            <vitals hp="3290.11306877694" hpRegen="8.5" mp="1674.8" mpRegen="3" />
            <attack physical="400.537548504614" magical="300.751329129412" random="30" critical="4" accuracy="5" attackSpeed="253" type="DUAL" range="40" distance="80" width="120" />
            <defence physical="400.375" magical="50.80341" />
            <attribute>
                <attack type="DARK" value="150" />
                <defence fire="80" water="80" wind="80" earth="80" holy="80" dark="80" default="100" />
            </attribute>
            <speed>
                <walk ground="64" />
                <run ground="200" />
            </speed>
        </stats>
        <status undying="false" canBeSown="true" />
        <skillList>
            <skill id="4408" level="10" /> <!--HP Increase (2x) -->
            <skill id="4409" level="1" /> <!--MP Increase (1x) -->
            <skill id="4410" level="15" /> <!--Strong P. Atk. -->
            <skill id="4411" level="11" /> <!--Average M. Atk. -->
            <skill id="4412" level="13" /> <!--Slightly Strong P. Def. -->
            <skill id="4413" level="9" /> <!--Slightly Weak M. Def. -->
            <skill id="4414" level="2" /> <!--Standard Type -->
            <skill id="4415" level="19" /> <!--Dual-Sword Weapons -->
            <skill id="4416" level="1" /> <!--Undead -->
            <skill id="5467" level="1" /> <!--Dark Attacks -->
            <skill id="6845" level="1" /> <!--Power Strike -->
        </skillList>
        <exCrtEffect>false</exCrtEffect>
        <sNpcPropHpRate>2</sNpcPropHpRate>
        <ai type="BALANCED" aggroRange="300" isAggressive="false">
            <clanList>
                <clan>DRAKOS</clan>
            </clanList>
        </ai>
        <dropLists>
            <death>
                <group chance="66">
                    <item id="57" min="100000" max="200000" chance="70" /> <!-- Adena -->
                </group>
            </death>
        </dropLists>
        <collision>
            <radius normal="16" />
            <height normal="27.2" />
        </collision>
    </npc>
</list>